[
    {
        "text": "SOURCE: 15041689.pdf\nIDENTITY: Candidate Profile (15041689.pdf)\nSUMMARY: HR Professional with over 15 years of experience in multi-unit businesses, expertise in developing and implementing HR plans, conflict resolution, employment protocol compliance, and staffing needs.\nSKILLS: ADP, Benefits, counseling, database, employee relations, hiring, HRIS, HR, Director, meetings, Enterprise, newspapers, payroll, PeopleSoft 8.0, PeopleSoft HRMS, Performance management, personnel, policies, processes, Recruitment, reporting, safety, TV",
        "metadata": {
            "source_file": "15041689.pdf",
            "department": "HR",
            "chunk_type": "profile"
        }
    },
    {
        "text": "SOURCE: 15041689.pdf\nJOB TITLE: HR Director\nCOMPANY: Company Name\nDATES: November 2007 - October 2014\nDESCRIPTION: Managed HR for New Kent horse track and 8 off-track betting sites, approximately 650 employees. Ensured compliance with federal and state laws, provided employee relations guidance, created fair policies, conducted performance assessments, and managed benefits administration.",
        "metadata": {
            "source_file": "15041689.pdf",
            "department": "HR",
            "chunk_type": "experience"
        }
    },
    {
        "text": "SOURCE: 15041689.pdf\nJOB TITLE: HR Generalist\nCOMPANY: Company Name\nDATES: October 2004 - March 2008\nDESCRIPTION: Managed HR for 30 TV stations and 1 communications company across the Southeast, approximately 2,000 employees. Handled FMLA, STD, LTD, and Worker's Comp, maintained job requisition database, provided recruitment/retention support.",
        "metadata": {
            "source_file": "15041689.pdf",
            "department": "HR",
            "chunk_type": "experience"
        }
    },
    {
        "text": "SOURCE: 15041689.pdf\nJOB TITLE: Benefits Administrator\nCOMPANY: Company Name\nDATES: February 2001 - January 2004\nDESCRIPTION: Administered benefit plans for 27 newspapers and TV stations, approximately 3,500 employees. Processed enrollments daily using PeopleSoft 8.0, assisted with annual Open Enrollment.",
        "metadata": {
            "source_file": "15041689.pdf",
            "department": "HR",
            "chunk_type": "experience"
        }
    },
    {
        "text": "SOURCE: 15041689.pdf\nJOB TITLE: HR Coordinator\nCOMPANY: Company Name\nDATES: January 2004 - October 2004\nDESCRIPTION: Managed HR for 4 daily and 2 weekly newspapers, approximately 400 employees. Reported payroll biweekly, recruited for open positions, maintained PeopleSoft HRMS database.",
        "metadata": {
            "source_file": "15041689.pdf",
            "department": "HR",
            "chunk_type": "experience"
        }
    },
    {
        "text": "SOURCE: 15041689.pdf\nDEGREE: Mathematics Computer Science Mathematics Computer Science\nINSTITUTION: Newberry College\nDATES: ",
        "metadata": {
            "source_file": "15041689.pdf",
            "department": "HR",
            "chunk_type": "education"
        }
    },
    {
        "text": "SOURCE: 15041689.pdf\nDEGREE: H.S. Diploma\nINSTITUTION: Batesburg Leesville High School\nDATES: ",
        "metadata": {
            "source_file": "15041689.pdf",
            "department": "HR",
            "chunk_type": "education"
        }
    }
]